pyisopach/__init__.py
pyisopach/element.py
pyisopach/molecule.py
pyisopach/periodic_table.py
tests/__init__.py
tests/test_element.py
tests/test_molecule.py
pyisopach-0.1.2.dist-info/LICENSE
pyisopach-0.1.2.dist-info/METADATA
pyisopach-0.1.2.dist-info/WHEEL
pyisopach-0.1.2.dist-info/top_level.txt
pyisopach-0.1.2.dist-info/RECORD
