Metadata-Version: 2.1
Name: pyisopach
Version: 0.1.2
Summary: This program calculates the isotopic distribution/pattern of a given chemical species.
Home-page: https://github.com/AberystwythSystemsBiology/pyISOPACh
Author: Keiron O'Shea
License: UNKNOWN
Keywords: cheminformatics,isotopic distribution,metabolomics
Platform: UNKNOWN
Classifier: Development Status :: 5 - Production/Stable
Classifier: Intended Audience :: Science/Research
Classifier: Programming Language :: Python :: 3.5
Classifier: Programming Language :: Python :: 3.7
Classifier: Topic :: Scientific/Engineering
Classifier: License :: OSI Approved :: MIT License
Requires-Python: >= 3.2
Requires-Dist: numpy (==1.16.0)
